spider/VERSION
spider/__init__.py
spider/requirements.txt
spider/setting.py
spider/buffer/__init__.py
spider/buffer/item_buffer.py
spider/buffer/request_buffer.py
spider/commands/__init__.py
spider/commands/cmdline.py
spider/commands/create_builder.py
spider/commands/shell.py
spider/core/__init__.py
spider/core/base_parser.py
spider/core/collector.py
spider/core/handle_failed_requests.py
spider/core/parser_control.py
spider/core/scheduler.py
spider/core/spiders/__init__.py
spider/core/spiders/batch_spider.py
spider/core/spiders/single_spider.py
spider/core/spiders/spider.py
spider/db/__init__.py
spider/db/memory_db.py
spider/db/mysqldb.py
spider/db/redisdb.py
spider/dedup/__init__.py
spider/dedup/bitarray.py
spider/dedup/bloomfilter.py
spider/dedup/expirefilter.py
spider/dedup/test.py
spider/network/__init__.py
spider/network/item.py
spider/network/proxy_pool.py
spider/network/request.py
spider/network/response.py
spider/network/selector.py
spider/network/user_agent.py
spider/templates/item_template.tmpl
spider/templates/parser_template.tmpl
spider/templates/spider/main.py
spider/templates/spider/setting.py
spider/templates/spider/items/__init__.py
spider/templates/spider/parsers/__init__.py
spider/utils/__init__.py
spider/utils/custom_argparse.py
spider/utils/export_data.py
spider/utils/log.py
spider/utils/redis_lock.py
spider/utils/tools.py
boris_spider-1.1.3.dist-info/LICENSE
boris_spider-1.1.3.dist-info/METADATA
boris_spider-1.1.3.dist-info/WHEEL
boris_spider-1.1.3.dist-info/entry_points.txt
boris_spider-1.1.3.dist-info/top_level.txt
boris_spider-1.1.3.dist-info/RECORD
