Metadata-Version: 2.1
Name: boris-spider
Version: 1.1.3
Summary: A high-level Web Crawling and Web Scraping framework
Home-page: https://github.com/Boris-code/boris-spider.git
Author: Boris
Author-email: boris@bzkj.tech
License: MIT
Platform: UNKNOWN
Classifier: Programming Language :: Python :: 3
Requires-Dist: better-exceptions (==0.2.2)
Requires-Dist: DBUtils (==1.3)
Requires-Dist: parsel (==1.5.2)
Requires-Dist: PyExecJS (==1.5.1)
Requires-Dist: PyMySQL (==0.9.3)
Requires-Dist: redis (==2.10.6)
Requires-Dist: requests (>=2.22.0)
Requires-Dist: bs4 (==0.0.1)
Requires-Dist: ipython (==7.14.0)
Requires-Dist: bitarray (==1.5.3)
Requires-Dist: redis-py-cluster (==1.3.4)
